perovskite_intercalation/__init__.py
perovskite_intercalation/perovskite_intercalation.py
perovskite_intercalation-0.1.2.dist-info/LICENSE.md
perovskite_intercalation-0.1.2.dist-info/METADATA
perovskite_intercalation-0.1.2.dist-info/WHEEL
perovskite_intercalation-0.1.2.dist-info/top_level.txt
perovskite_intercalation-0.1.2.dist-info/RECORD
