Metadata-Version: 2.1
Name: perovskite-intercalation
Version: 0.1.2
Summary: Routines to create intercalated perovskite crystals
Home-page: https://github.com/kevinwhitham/perovskite_intercalation
Author: Kevin Whitham
Author-email: kevin.whitham@gmail.com
Classifier: Programming Language :: Python :: 3
Classifier: License :: OSI Approved :: GNU General Public License v3 or later (GPLv3+)
Classifier: Operating System :: OS Independent
Requires-Python: >=3
License-File: LICENSE.md
Requires-Dist: ase (>=3.21.1)
Requires-Dist: pymatgen (>=2022.0.5)
Requires-Dist: networkx (>=2.5)
Requires-Dist: numpy (>=1.20.2)
Requires-Dist: matplotlib (>=3.4.1)
Requires-Dist: pillow (>=8.1.2)
